yuid/__init__.py
yuid/yuid.py
yuid-0.1.1.dist-info/LICENSE
yuid-0.1.1.dist-info/METADATA
yuid-0.1.1.dist-info/WHEEL
yuid-0.1.1.dist-info/top_level.txt
yuid-0.1.1.dist-info/RECORD
