Metadata-Version: 2.1
Name: yuid
Version: 0.1.1
Summary: youtube-like UUIDs
Home-page: https://github.com/ogastorga/yuid
Author: Og Astorga
Author-email: og@ogastorga.com
License: UNKNOWN
Keywords: uuid
Platform: UNKNOWN
Classifier: Intended Audience :: Developers
Classifier: Programming Language :: Python :: 3
Classifier: License :: OSI Approved :: MIT License
